tts_webui_extension/audiocraft/__init__.py
tts_webui_extension/audiocraft/main.py
tts_webui_extension/audiocraft/magnet/__init__.py
tts_webui_extension/audiocraft/magnet/magnet_tab.py
tts_webui_extension/audiocraft/musicgen/__init__.py
tts_webui_extension/audiocraft/musicgen/musicgen_tab.py
tts_webui_extension_audiocraft-0.0.4.dist-info/licenses/LICENSE
tts_webui_extension_audiocraft-0.0.4.dist-info/METADATA
tts_webui_extension_audiocraft-0.0.4.dist-info/WHEEL
tts_webui_extension_audiocraft-0.0.4.dist-info/top_level.txt
tts_webui_extension_audiocraft-0.0.4.dist-info/RECORD
