Metadata-Version: 2.4
Name: tts_webui_extension.audiocraft
Version: 0.0.4
Summary: Audiocraft provides MusicGen and MAGNeT models for high-quality music and audio generation
Author: rsxdalv
Project-URL: Homepage, https://github.com/rsxdalv/tts_webui_extension.audiocraft
Classifier: Programming Language :: Python :: 3
Classifier: License :: OSI Approved :: MIT License
Classifier: Operating System :: OS Independent
Requires-Python: >=3.7
License-File: LICENSE
Requires-Dist: tts-webui.audiocraft>=1.4.0a2
Requires-Dist: spacy>=3.7.6
Requires-Dist: numpy<2
Dynamic: license-file
